semantics/__init__.py
semantics/server.py
semeval/__init__.py
semeval/common.py
semeval/download.py
semeval/embeddings.py
semeval/relatedness.py
semeval/server.py
semeval/serviecs/__init__.py
semeval/serviecs/embeddings.py
semeval-1.0.3.dist-info/LICENSE
semeval-1.0.3.dist-info/METADATA
semeval-1.0.3.dist-info/WHEEL
semeval-1.0.3.dist-info/top_level.txt
semeval-1.0.3.dist-info/RECORD
