Metadata-Version: 2.1
Name: semeval
Version: 1.0.3
Summary: A library for working with semantics in multiple languages..
Home-page: https://github.com/mokha/semantics
Author: Khalid Alnajjar
Author-email: khldalnajjar@gmail.com
License: Apache License, Version 2.0
Project-URL: Bug Reports, https://github.com/mokha/semantics/issues
Project-URL: Wiki, https://github.com/mokha/semantics/wiki
Project-URL: Developer, https://www.khalidalnajjar.com/
Keywords: NLP,semeval,languages,endangered languages
Platform: UNKNOWN
Classifier: Development Status :: 5 - Production/Stable
Classifier: Intended Audience :: Developers
Classifier: Intended Audience :: Science/Research
Classifier: Topic :: Text Processing :: Linguistic
Classifier: Programming Language :: Python :: 3
License-File: LICENSE
Requires-Dist: mikatools
Requires-Dist: argparse
Requires-Dist: numpy
Requires-Dist: gensim
Requires-Dist: fastapi
Requires-Dist: uvicorn
Requires-Dist: ujson
Requires-Dist: requests
Requires-Dist: scikit-learn
Requires-Dist: hickle
